my_package/F_AttributeValidator4.cpython-312-x86_64-linux-gnu.so
my_package/F_Dbconfigreader.cpython-312-x86_64-linux-gnu.so
my_package/F_Dbreader.cpython-312-x86_64-linux-gnu.so
my_package/F_Dbwriters.cpython-312-x86_64-linux-gnu.so
my_package/F_Extract_channels.cpython-312-x86_64-linux-gnu.so
my_package/F_Movefiles.cpython-312-x86_64-linux-gnu.so
my_package/F_UtilityFunctions.cpython-312-x86_64-linux-gnu.so
my_package/F_csvtxtreader.cpython-312-x86_64-linux-gnu.so
my_package/F_databaseconnect.cpython-312-x86_64-linux-gnu.so
my_package/F_datamasking.cpython-312-x86_64-linux-gnu.so
my_package/F_dataunmasking.cpython-312-x86_64-linux-gnu.so
my_package/F_delta_table_load.cpython-312-x86_64-linux-gnu.so
my_package/F_delta_table_load_2.cpython-312-x86_64-linux-gnu.so
my_package/F_filereader.cpython-312-x86_64-linux-gnu.so
my_package/F_filereader2.cpython-312-x86_64-linux-gnu.so
my_package/F_iot_schema.cpython-312-x86_64-linux-gnu.so
my_package/F_iotdata_reader.cpython-312-x86_64-linux-gnu.so
my_package/F_json_2reader.cpython-312-x86_64-linux-gnu.so
my_package/F_jsonreader.cpython-312-x86_64-linux-gnu.so
my_package/F_kafka_reader.cpython-312-x86_64-linux-gnu.so
my_package/F_kafka_schema.cpython-312-x86_64-linux-gnu.so
my_package/F_logs.cpython-312-x86_64-linux-gnu.so
my_package/F_monit.cpython-312-x86_64-linux-gnu.so
my_package/F_parquetreader.cpython-312-x86_64-linux-gnu.so
my_package/F_stream_powerbi.cpython-312-x86_64-linux-gnu.so
my_package/F_xmlreader.cpython-312-x86_64-linux-gnu.so
my_package/NB_stream_to_powerbi.cpython-312-x86_64-linux-gnu.so
my_package/__init__.py
my_package/encryption_nb_dqf_validation.cpython-312-x86_64-linux-gnu.so
my_package/get_sparkutils.cpython-312-x86_64-linux-gnu.so
my_package/public.pem
bsh_file_validation_check-0.2.8.dist-info/METADATA
bsh_file_validation_check-0.2.8.dist-info/WHEEL
bsh_file_validation_check-0.2.8.dist-info/top_level.txt
bsh_file_validation_check-0.2.8.dist-info/RECORD
