Metadata-Version: 2.4
Name: bsh-file-validation-check
Version: 0.2.8
Requires-Python: >=3.10,<3.13
Requires-Dist: cryptography
Requires-Dist: msal==1.32.3
Requires-Dist: tinytag==2.1.0
Requires-Dist: moviepy==1.0.3
Dynamic: requires-dist
Dynamic: requires-python
